Metadata-Version: 2.1
Name: topsis-101903570
Version: 4.1.0
Summary: Python package to implement TOPSIS
Home-page: https://github.com/saksham02112000/topsis-101903570
Author: Saksham
Author-email: sakshamsrini@gmail.com
License: MIT
Platform: UNKNOWN
Classifier: License :: OSI Approved :: MIT License
Classifier: Programming Language :: Python :: 3
Classifier: Programming Language :: Python :: 3.7
